{
    "type": "Program",
    "statements": [
        {
            "FunctionDeclarationStatement": {
                "type": "FunctionDeclarationStatement",
                "header": {
                    "type": "FunctionHeader",
                    "name": {
                        "type": "IdentifierLiteral",
                        "identifier": "main"
                    },
                    "params": [],
                    "ret_type": "int"
                },
                "body": {
                    "type": "BlockStatement",
                    "statements": [
                        {
                            "type": "ExpressionStatement",
                            "expr": {
                                "type": "CallExpression",
                                "callee": {
                                    "type": "IdentifierLiteral",
                                    "identifier": "print"
                                },
                                "args": [
                                    {
                                        "type": "CallExpression",
                                        "callee": {
                                            "type": "IdentifierLiteral",
                                            "identifier": "type"
                                        },
                                        "args": [
                                            {
                                                "type": "StringLiteral",
                                                "string": ""
                                            }
                                        ]
                                    }
                                ]
                            }
                        },
                        {
                            "type": "ReturnStatement",
                            "return_value": {
                                "type": "IntegerLiteral",
                                "integer": 0
                            }
                        }
                    ]
                }
            }
        }
    ]
}